beatmup-2.1.1.data/purelib/beatmup.cp310-win_amd64.pyd
beatmup-2.1.1.data/purelib/beatmup_keras.py
beatmup-2.1.1.data/purelib/beatmup.egg-info/PKG-INFO
beatmup-2.1.1.data/purelib/beatmup.egg-info/SOURCES.txt
beatmup-2.1.1.data/purelib/beatmup.egg-info/dependency_links.txt
beatmup-2.1.1.data/purelib/beatmup.egg-info/top_level.txt
beatmup-2.1.1.dist-info/METADATA
beatmup-2.1.1.dist-info/WHEEL
beatmup-2.1.1.dist-info/top_level.txt
beatmup-2.1.1.dist-info/RECORD
