Metadata-Version: 2.1
Name: beatmup
Version: 2.1.1
Summary: Image and signal asynchronous processing library. A lot of fun
Home-page: https://github.com/lnstadrum/beatmup
Author: lnstadrum
Author-email: 
License: UNKNOWN
Platform: Windows
Classifier: Programming Language :: Python :: 3
Classifier: Topic :: Scientific/Engineering :: Image Processing
Classifier: License :: OSI Approved :: GNU General Public License v3 (GPLv3)
